pyaga8-0.1.15.dist-info/METADATA
pyaga8-0.1.15.dist-info/WHEEL
pyaga8-0.1.15.dist-info/licenses/LICENSE
pyaga8/__init__.py
pyaga8/pyaga8.cpython-311-darwin.so
pyaga8-0.1.15.dist-info/RECORD
