Metadata-Version: 2.4
Name: pyaga8
Version: 0.1.15
Classifier: Programming Language :: Rust
Classifier: Programming Language :: Python :: Implementation :: CPython
Classifier: Programming Language :: Python :: Implementation :: PyPy
License-File: LICENSE
Summary: Python package for calculating gas properties using the AGA8 equations GERG-2008 and DETAIL
Keywords: AGA8,gas properties,GERG-2008,DETAIL
Author: Roy Vegard Ovesen, Christian Hågenvik
License-Expression: MIT License
Requires-Python: >=3.8
Project-URL: homepage, https://github.com/equinor/pyaga8
